Topsis_Harshita_Saxena_102003497/topsis.py
Topsis_Harshita_Saxena_102003497-0.4.dist-info/LICENSE.txt
Topsis_Harshita_Saxena_102003497-0.4.dist-info/METADATA
Topsis_Harshita_Saxena_102003497-0.4.dist-info/WHEEL
Topsis_Harshita_Saxena_102003497-0.4.dist-info/entry_points.txt
Topsis_Harshita_Saxena_102003497-0.4.dist-info/top_level.txt
Topsis_Harshita_Saxena_102003497-0.4.dist-info/RECORD
