Metadata-Version: 2.1
Name: Topsis-Harshita-Saxena-102003497
Version: 0.4
Summary: Given package has the code for topsis, which is one of the techniques used for multiple criteria decision making. It chooses the Euclidean distance from the ideal solution and greatest distance from the negative ideal solution. 
Home-page: UNKNOWN
Author: Harshita Saxena
License: UNKNOWN
Platform: UNKNOWN
Requires-Dist: pandas
